binwalkpy-0.1.1.dist-info/METADATA
binwalkpy-0.1.1.dist-info/WHEEL
binwalkpy/__init__.py
binwalkpy/binwalkpy.cp313-win_amd64.pyd
binwalkpy-0.1.1.dist-info/RECORD
