Metadata-Version: 2.4
Name: binwalkpy
Version: 0.1.1
